mattak/Dataset.py
mattak/__init__.py
mattak/backends/__init__.py
mattak/backends/pyroot/__init__.py
mattak/backends/pyroot/dataset.py
mattak/backends/pyroot/mattakloader.py
mattak/backends/uproot/__init__.py
mattak/backends/uproot/dataset.py
mattak/build/bin/rno-g-combine
mattak/build/bin/rno-g-convert-run
mattak/build/bin/rno-g-make-eventlist
mattak/build/bin/rno-g-make-eventlists
mattak/build/bin/rno-g-summary-tree
mattak/build/include/mattak/Constants.h
mattak/build/include/mattak/Converter.h
mattak/build/include/mattak/DAQStatus.h
mattak/build/include/mattak/Dataset.h
mattak/build/include/mattak/GNSS.h
mattak/build/include/mattak/Header.h
mattak/build/include/mattak/Pedestals.h
mattak/build/include/mattak/RunInfo.h
mattak/build/include/mattak/Sensors.h
mattak/build/include/mattak/TriggerInfo.h
mattak/build/include/mattak/Version.h
mattak/build/include/mattak/VoltageCalibration.h
mattak/build/include/mattak/Waveforms.h
mattak/build/lib/libmattak.so
mattak/build/lib/libmattak_rdict.pcm
src/Converter.cc
src/DAQStatus.cc
src/Dataset.cc
src/GNSS.cc
src/Header.cc
src/LinkDef.h
src/Pedestals.cc
src/RunInfo.cc
src/Sensors.cc
src/TriggerInfo.cc
src/Version.cc.in
src/VoltageCalibration.cc
src/Waveforms.cc
src/mattak/Constants.h
src/mattak/Converter.h
src/mattak/DAQStatus.h
src/mattak/Dataset.h
src/mattak/GNSS.h
src/mattak/Header.h
src/mattak/Pedestals.h
src/mattak/RunInfo.h
src/mattak/Sensors.h
src/mattak/TriggerInfo.h
src/mattak/Version.h
src/mattak/VoltageCalibration.h
src/mattak/Waveforms.h
mattak-0.1.1.dist-info/METADATA
mattak-0.1.1.dist-info/WHEEL
mattak-0.1.1.dist-info/entry_points.txt
mattak-0.1.1.dist-info/licenses/AUTHORS
mattak-0.1.1.dist-info/RECORD
