Metadata-Version: 2.1
Name: mattak
Version: 0.1.1
Summary: Mattak is (will eventually be) a multilingual package containing readers and helpers for RNO-G in C++, Python (via both uproot and PyROOT) and maybe even JS (via rootjs).
Author: Cosmin Deaconu, email=<cozzyd@kicp.uchicago.edu>
Requires-Dist: numpy
Requires-Dist: uproot
Requires-Dist: awkward<2
License-File: AUTHORS
